[{"generated": 1718611019, "type": "Internet Name", "data": "google.com", "module": "SpiderFoot UI", "source": "google.com"},
{"generated": 1718611020, "type": "Domain Name", "data": "google.com", "module": "SpiderFoot UI", "source": "google.com"}]
[{"generated": 1718611774, "type": "Internet Name", "data": "google.com", "module": "SpiderFoot UI", "source": "google.com"},
{"generated": 1718611774, "type": "Domain Name", "data": "google.com", "module": "SpiderFoot UI", "source": "google.com"}]
[{"generated": 1718611944, "type": "Internet Name", "data": "google.com", "module": "SpiderFoot UI", "source": "google.com"},
{"generated": 1718611944, "type": "Domain Name", "data": "google.com", "module": "SpiderFoot UI", "source": "google.com"}]
[{"generated": 1718612328, "type": "Internet Name", "data": "google.com", "module": "SpiderFoot UI", "source": "google.com"},
{"generated": 1718612328, "type": "Domain Name", "data": "google.com", "module": "SpiderFoot UI", "source": "google.com"}]
[{"generated": 1718612390, "type": "Internet Name", "data": "google.com", "module": "SpiderFoot UI", "source": "google.com"},
{"generated": 1718612390, "type": "Domain Name", "data": "google.com", "module": "SpiderFoot UI", "source": "google.com"}]
